{
	"id": "1a2e7599-a355-437c-a16a-13a7592b273c",
	"prevId": "0196c6e0-ebdc-416b-aa60-281badaabbd5",
	"version": "7",
	"dialect": "postgresql",
	"tables": {
		"public.feature_flags": {
			"name": "feature_flags",
			"schema": "",
			"columns": {
				"name": {
					"name": "name",
					"type": "text",
					"primaryKey": true,
					"notNull": true
				},
				"enabled": {
					"name": "enabled",
					"type": "boolean",
					"primaryKey": false,
					"notNull": true,
					"default": false
				},
				"updated_at": {
					"name": "updated_at",
					"type": "timestamp",
					"primaryKey": false,
					"notNull": true,
					"default": "now()"
				}
			},
			"indexes": {},
			"foreignKeys": {},
			"compositePrimaryKeys": {},
			"uniqueConstraints": {},
			"policies": {},
			"checkConstraints": {},
			"isRLSEnabled": false
		},
		"public.report_comments": {
			"name": "report_comments",
			"schema": "",
			"columns": {
				"id": {
					"name": "id",
					"type": "text",
					"primaryKey": true,
					"notNull": true
				},
				"report_id": {
					"name": "report_id",
					"type": "text",
					"primaryKey": false,
					"notNull": true
				},
				"parent_id": {
					"name": "parent_id",
					"type": "text",
					"primaryKey": false,
					"notNull": false
				},
				"author_id": {
					"name": "author_id",
					"type": "text",
					"primaryKey": false,
					"notNull": true
				},
				"body": {
					"name": "body",
					"type": "text",
					"primaryKey": false,
					"notNull": true
				},
				"upvote_count": {
					"name": "upvote_count",
					"type": "integer",
					"primaryKey": false,
					"notNull": true,
					"default": 0
				},
				"downvote_count": {
					"name": "downvote_count",
					"type": "integer",
					"primaryKey": false,
					"notNull": true,
					"default": 0
				},
				"deleted_at": {
					"name": "deleted_at",
					"type": "timestamp",
					"primaryKey": false,
					"notNull": false
				},
				"created_at": {
					"name": "created_at",
					"type": "timestamp",
					"primaryKey": false,
					"notNull": true,
					"default": "now()"
				},
				"updated_at": {
					"name": "updated_at",
					"type": "timestamp",
					"primaryKey": false,
					"notNull": true,
					"default": "now()"
				}
			},
			"indexes": {
				"comment_report_id_idx": {
					"name": "comment_report_id_idx",
					"columns": [
						{
							"expression": "report_id",
							"isExpression": false,
							"asc": true,
							"nulls": "last"
						}
					],
					"isUnique": false,
					"concurrently": false,
					"method": "btree",
					"with": {}
				},
				"comment_parent_id_idx": {
					"name": "comment_parent_id_idx",
					"columns": [
						{
							"expression": "parent_id",
							"isExpression": false,
							"asc": true,
							"nulls": "last"
						}
					],
					"isUnique": false,
					"concurrently": false,
					"method": "btree",
					"with": {}
				},
				"comment_author_id_idx": {
					"name": "comment_author_id_idx",
					"columns": [
						{
							"expression": "author_id",
							"isExpression": false,
							"asc": true,
							"nulls": "last"
						}
					],
					"isUnique": false,
					"concurrently": false,
					"method": "btree",
					"with": {}
				}
			},
			"foreignKeys": {
				"report_comments_report_id_reports_id_fk": {
					"name": "report_comments_report_id_reports_id_fk",
					"tableFrom": "report_comments",
					"tableTo": "reports",
					"columnsFrom": ["report_id"],
					"columnsTo": ["id"],
					"onDelete": "cascade",
					"onUpdate": "no action"
				},
				"report_comments_author_id_users_id_fk": {
					"name": "report_comments_author_id_users_id_fk",
					"tableFrom": "report_comments",
					"tableTo": "users",
					"columnsFrom": ["author_id"],
					"columnsTo": ["id"],
					"onDelete": "cascade",
					"onUpdate": "no action"
				}
			},
			"compositePrimaryKeys": {},
			"uniqueConstraints": {},
			"policies": {},
			"checkConstraints": {},
			"isRLSEnabled": false
		},
		"public.report_followers": {
			"name": "report_followers",
			"schema": "",
			"columns": {
				"id": {
					"name": "id",
					"type": "text",
					"primaryKey": true,
					"notNull": true
				},
				"user_id": {
					"name": "user_id",
					"type": "text",
					"primaryKey": false,
					"notNull": true
				},
				"report_id": {
					"name": "report_id",
					"type": "text",
					"primaryKey": false,
					"notNull": true
				},
				"created_at": {
					"name": "created_at",
					"type": "timestamp",
					"primaryKey": false,
					"notNull": true,
					"default": "now()"
				}
			},
			"indexes": {
				"follower_user_report_idx": {
					"name": "follower_user_report_idx",
					"columns": [
						{
							"expression": "user_id",
							"isExpression": false,
							"asc": true,
							"nulls": "last"
						},
						{
							"expression": "report_id",
							"isExpression": false,
							"asc": true,
							"nulls": "last"
						}
					],
					"isUnique": true,
					"concurrently": false,
					"method": "btree",
					"with": {}
				}
			},
			"foreignKeys": {
				"report_followers_user_id_users_id_fk": {
					"name": "report_followers_user_id_users_id_fk",
					"tableFrom": "report_followers",
					"tableTo": "users",
					"columnsFrom": ["user_id"],
					"columnsTo": ["id"],
					"onDelete": "cascade",
					"onUpdate": "no action"
				},
				"report_followers_report_id_reports_id_fk": {
					"name": "report_followers_report_id_reports_id_fk",
					"tableFrom": "report_followers",
					"tableTo": "reports",
					"columnsFrom": ["report_id"],
					"columnsTo": ["id"],
					"onDelete": "cascade",
					"onUpdate": "no action"
				}
			},
			"compositePrimaryKeys": {},
			"uniqueConstraints": {},
			"policies": {},
			"checkConstraints": {},
			"isRLSEnabled": false
		},
		"public.report_votes": {
			"name": "report_votes",
			"schema": "",
			"columns": {
				"id": {
					"name": "id",
					"type": "text",
					"primaryKey": true,
					"notNull": true
				},
				"user_id": {
					"name": "user_id",
					"type": "text",
					"primaryKey": false,
					"notNull": true
				},
				"report_id": {
					"name": "report_id",
					"type": "text",
					"primaryKey": false,
					"notNull": false
				},
				"comment_id": {
					"name": "comment_id",
					"type": "text",
					"primaryKey": false,
					"notNull": false
				},
				"vote_type": {
					"name": "vote_type",
					"type": "vote_type",
					"typeSchema": "public",
					"primaryKey": false,
					"notNull": true
				},
				"created_at": {
					"name": "created_at",
					"type": "timestamp",
					"primaryKey": false,
					"notNull": true,
					"default": "now()"
				}
			},
			"indexes": {
				"vote_user_report_idx": {
					"name": "vote_user_report_idx",
					"columns": [
						{
							"expression": "user_id",
							"isExpression": false,
							"asc": true,
							"nulls": "last"
						},
						{
							"expression": "report_id",
							"isExpression": false,
							"asc": true,
							"nulls": "last"
						}
					],
					"isUnique": true,
					"where": "\"report_votes\".\"report_id\" IS NOT NULL",
					"concurrently": false,
					"method": "btree",
					"with": {}
				},
				"vote_user_comment_idx": {
					"name": "vote_user_comment_idx",
					"columns": [
						{
							"expression": "user_id",
							"isExpression": false,
							"asc": true,
							"nulls": "last"
						},
						{
							"expression": "comment_id",
							"isExpression": false,
							"asc": true,
							"nulls": "last"
						}
					],
					"isUnique": true,
					"where": "\"report_votes\".\"comment_id\" IS NOT NULL",
					"concurrently": false,
					"method": "btree",
					"with": {}
				}
			},
			"foreignKeys": {
				"report_votes_user_id_users_id_fk": {
					"name": "report_votes_user_id_users_id_fk",
					"tableFrom": "report_votes",
					"tableTo": "users",
					"columnsFrom": ["user_id"],
					"columnsTo": ["id"],
					"onDelete": "cascade",
					"onUpdate": "no action"
				},
				"report_votes_report_id_reports_id_fk": {
					"name": "report_votes_report_id_reports_id_fk",
					"tableFrom": "report_votes",
					"tableTo": "reports",
					"columnsFrom": ["report_id"],
					"columnsTo": ["id"],
					"onDelete": "cascade",
					"onUpdate": "no action"
				},
				"report_votes_comment_id_report_comments_id_fk": {
					"name": "report_votes_comment_id_report_comments_id_fk",
					"tableFrom": "report_votes",
					"tableTo": "report_comments",
					"columnsFrom": ["comment_id"],
					"columnsTo": ["id"],
					"onDelete": "cascade",
					"onUpdate": "no action"
				}
			},
			"compositePrimaryKeys": {},
			"uniqueConstraints": {},
			"policies": {},
			"checkConstraints": {},
			"isRLSEnabled": false
		},
		"public.reports": {
			"name": "reports",
			"schema": "",
			"columns": {
				"id": {
					"name": "id",
					"type": "text",
					"primaryKey": true,
					"notNull": true
				},
				"title": {
					"name": "title",
					"type": "text",
					"primaryKey": false,
					"notNull": true
				},
				"body": {
					"name": "body",
					"type": "text",
					"primaryKey": false,
					"notNull": true
				},
				"category": {
					"name": "category",
					"type": "report_category",
					"typeSchema": "public",
					"primaryKey": false,
					"notNull": true
				},
				"status": {
					"name": "status",
					"type": "report_status",
					"typeSchema": "public",
					"primaryKey": false,
					"notNull": true,
					"default": "'open'"
				},
				"author_id": {
					"name": "author_id",
					"type": "text",
					"primaryKey": false,
					"notNull": true
				},
				"upvote_count": {
					"name": "upvote_count",
					"type": "integer",
					"primaryKey": false,
					"notNull": true,
					"default": 0
				},
				"downvote_count": {
					"name": "downvote_count",
					"type": "integer",
					"primaryKey": false,
					"notNull": true,
					"default": 0
				},
				"comment_count": {
					"name": "comment_count",
					"type": "integer",
					"primaryKey": false,
					"notNull": true,
					"default": 0
				},
				"follower_count": {
					"name": "follower_count",
					"type": "integer",
					"primaryKey": false,
					"notNull": true,
					"default": 0
				},
				"is_pinned": {
					"name": "is_pinned",
					"type": "boolean",
					"primaryKey": false,
					"notNull": true,
					"default": false
				},
				"deleted_at": {
					"name": "deleted_at",
					"type": "timestamp",
					"primaryKey": false,
					"notNull": false
				},
				"created_at": {
					"name": "created_at",
					"type": "timestamp",
					"primaryKey": false,
					"notNull": true,
					"default": "now()"
				},
				"updated_at": {
					"name": "updated_at",
					"type": "timestamp",
					"primaryKey": false,
					"notNull": true,
					"default": "now()"
				}
			},
			"indexes": {
				"report_author_id_idx": {
					"name": "report_author_id_idx",
					"columns": [
						{
							"expression": "author_id",
							"isExpression": false,
							"asc": true,
							"nulls": "last"
						}
					],
					"isUnique": false,
					"concurrently": false,
					"method": "btree",
					"with": {}
				},
				"report_category_deleted_idx": {
					"name": "report_category_deleted_idx",
					"columns": [
						{
							"expression": "category",
							"isExpression": false,
							"asc": true,
							"nulls": "last"
						},
						{
							"expression": "deleted_at",
							"isExpression": false,
							"asc": true,
							"nulls": "last"
						}
					],
					"isUnique": false,
					"concurrently": false,
					"method": "btree",
					"with": {}
				},
				"report_status_deleted_idx": {
					"name": "report_status_deleted_idx",
					"columns": [
						{
							"expression": "status",
							"isExpression": false,
							"asc": true,
							"nulls": "last"
						},
						{
							"expression": "deleted_at",
							"isExpression": false,
							"asc": true,
							"nulls": "last"
						}
					],
					"isUnique": false,
					"concurrently": false,
					"method": "btree",
					"with": {}
				},
				"report_created_at_deleted_idx": {
					"name": "report_created_at_deleted_idx",
					"columns": [
						{
							"expression": "created_at",
							"isExpression": false,
							"asc": true,
							"nulls": "last"
						},
						{
							"expression": "deleted_at",
							"isExpression": false,
							"asc": true,
							"nulls": "last"
						}
					],
					"isUnique": false,
					"concurrently": false,
					"method": "btree",
					"with": {}
				},
				"report_category_status_deleted_idx": {
					"name": "report_category_status_deleted_idx",
					"columns": [
						{
							"expression": "category",
							"isExpression": false,
							"asc": true,
							"nulls": "last"
						},
						{
							"expression": "status",
							"isExpression": false,
							"asc": true,
							"nulls": "last"
						},
						{
							"expression": "deleted_at",
							"isExpression": false,
							"asc": true,
							"nulls": "last"
						}
					],
					"isUnique": false,
					"concurrently": false,
					"method": "btree",
					"with": {}
				}
			},
			"foreignKeys": {
				"reports_author_id_users_id_fk": {
					"name": "reports_author_id_users_id_fk",
					"tableFrom": "reports",
					"tableTo": "users",
					"columnsFrom": ["author_id"],
					"columnsTo": ["id"],
					"onDelete": "cascade",
					"onUpdate": "no action"
				}
			},
			"compositePrimaryKeys": {},
			"uniqueConstraints": {},
			"policies": {},
			"checkConstraints": {},
			"isRLSEnabled": false
		},
		"public.sessions": {
			"name": "sessions",
			"schema": "",
			"columns": {
				"id": {
					"name": "id",
					"type": "text",
					"primaryKey": true,
					"notNull": true
				},
				"user_id": {
					"name": "user_id",
					"type": "text",
					"primaryKey": false,
					"notNull": true
				},
				"expires_at": {
					"name": "expires_at",
					"type": "timestamp",
					"primaryKey": false,
					"notNull": true
				},
				"created_at": {
					"name": "created_at",
					"type": "timestamp",
					"primaryKey": false,
					"notNull": true,
					"default": "now()"
				}
			},
			"indexes": {
				"session_user_id_idx": {
					"name": "session_user_id_idx",
					"columns": [
						{
							"expression": "user_id",
							"isExpression": false,
							"asc": true,
							"nulls": "last"
						}
					],
					"isUnique": false,
					"concurrently": false,
					"method": "btree",
					"with": {}
				}
			},
			"foreignKeys": {
				"sessions_user_id_users_id_fk": {
					"name": "sessions_user_id_users_id_fk",
					"tableFrom": "sessions",
					"tableTo": "users",
					"columnsFrom": ["user_id"],
					"columnsTo": ["id"],
					"onDelete": "cascade",
					"onUpdate": "no action"
				}
			},
			"compositePrimaryKeys": {},
			"uniqueConstraints": {},
			"policies": {},
			"checkConstraints": {},
			"isRLSEnabled": false
		},
		"public.users": {
			"name": "users",
			"schema": "",
			"columns": {
				"id": {
					"name": "id",
					"type": "text",
					"primaryKey": true,
					"notNull": true
				},
				"email": {
					"name": "email",
					"type": "text",
					"primaryKey": false,
					"notNull": true
				},
				"google_id": {
					"name": "google_id",
					"type": "text",
					"primaryKey": false,
					"notNull": true
				},
				"name": {
					"name": "name",
					"type": "text",
					"primaryKey": false,
					"notNull": false
				},
				"picture": {
					"name": "picture",
					"type": "text",
					"primaryKey": false,
					"notNull": false
				},
				"is_admin": {
					"name": "is_admin",
					"type": "boolean",
					"primaryKey": false,
					"notNull": true,
					"default": false
				},
				"created_at": {
					"name": "created_at",
					"type": "timestamp",
					"primaryKey": false,
					"notNull": true,
					"default": "now()"
				}
			},
			"indexes": {},
			"foreignKeys": {},
			"compositePrimaryKeys": {},
			"uniqueConstraints": {
				"users_email_unique": {
					"name": "users_email_unique",
					"nullsNotDistinct": false,
					"columns": ["email"]
				},
				"users_google_id_unique": {
					"name": "users_google_id_unique",
					"nullsNotDistinct": false,
					"columns": ["google_id"]
				}
			},
			"policies": {},
			"checkConstraints": {},
			"isRLSEnabled": false
		},
		"public.waitlist_entries": {
			"name": "waitlist_entries",
			"schema": "",
			"columns": {
				"id": {
					"name": "id",
					"type": "text",
					"primaryKey": true,
					"notNull": true
				},
				"email": {
					"name": "email",
					"type": "text",
					"primaryKey": false,
					"notNull": true
				},
				"locale": {
					"name": "locale",
					"type": "text",
					"primaryKey": false,
					"notNull": true,
					"default": "'en'"
				},
				"confirmation_token": {
					"name": "confirmation_token",
					"type": "text",
					"primaryKey": false,
					"notNull": true
				},
				"email_confirmed": {
					"name": "email_confirmed",
					"type": "boolean",
					"primaryKey": false,
					"notNull": true,
					"default": false
				},
				"created_at": {
					"name": "created_at",
					"type": "timestamp",
					"primaryKey": false,
					"notNull": true,
					"default": "now()"
				},
				"confirmed_at": {
					"name": "confirmed_at",
					"type": "timestamp",
					"primaryKey": false,
					"notNull": false
				}
			},
			"indexes": {
				"email_idx": {
					"name": "email_idx",
					"columns": [
						{
							"expression": "email",
							"isExpression": false,
							"asc": true,
							"nulls": "last"
						}
					],
					"isUnique": false,
					"concurrently": false,
					"method": "btree",
					"with": {}
				},
				"confirmation_token_idx": {
					"name": "confirmation_token_idx",
					"columns": [
						{
							"expression": "confirmation_token",
							"isExpression": false,
							"asc": true,
							"nulls": "last"
						}
					],
					"isUnique": false,
					"concurrently": false,
					"method": "btree",
					"with": {}
				}
			},
			"foreignKeys": {},
			"compositePrimaryKeys": {},
			"uniqueConstraints": {
				"waitlist_entries_email_unique": {
					"name": "waitlist_entries_email_unique",
					"nullsNotDistinct": false,
					"columns": ["email"]
				},
				"waitlist_entries_confirmation_token_unique": {
					"name": "waitlist_entries_confirmation_token_unique",
					"nullsNotDistinct": false,
					"columns": ["confirmation_token"]
				}
			},
			"policies": {},
			"checkConstraints": {},
			"isRLSEnabled": false
		}
	},
	"enums": {
		"public.report_category": {
			"name": "report_category",
			"schema": "public",
			"values": ["bug", "feature_request", "question", "discussion"]
		},
		"public.report_status": {
			"name": "report_status",
			"schema": "public",
			"values": [
				"open",
				"under_review",
				"planned",
				"in_progress",
				"completed",
				"closed",
				"wont_fix"
			]
		},
		"public.vote_type": {
			"name": "vote_type",
			"schema": "public",
			"values": ["up", "down"]
		}
	},
	"schemas": {},
	"sequences": {},
	"roles": {},
	"policies": {},
	"views": {},
	"_meta": {
		"columns": {},
		"schemas": {},
		"tables": {}
	}
}
